ingestion_app/__init__.py
ingestion_app/my_cli_app.py
ingestion_app/process_data.py
ingestion_app-0.6.dist-info/METADATA
ingestion_app-0.6.dist-info/WHEEL
ingestion_app-0.6.dist-info/entry_points.txt
ingestion_app-0.6.dist-info/top_level.txt
ingestion_app-0.6.dist-info/RECORD
