Metadata-Version: 2.1
Name: ingestion-app
Version: 0.6
Requires-Dist: click
